{"sheet_structure":{"title":"","sections":{"1":{"value":"1. \u0417\u0435\u043c\u043b\u044f\u043d\u044b\u0435 \u0438 \u043f\u043e\u0434\u0433\u043e\u0442\u043e\u0432\u0438\u0442\u0435\u043b\u044c\u043d\u044b\u0435 \u0440\u0430\u0431\u043e\u0442\u044b","colIndex":0,"rowIndex":10,"labourItems":[{"labourNumber":"1.","labourTitle":"\u0420\u0430\u0437\u0431\u0438\u0432\u043a\u0430  \u043f\u043b\u043e\u0449\u0430\u0434\u043a\u0438 \u0441 \u0432\u044b\u043d\u043e\u0441\u043e\u043c \u043e\u0441\u0435\u0439 \u0441 \u043e\u0442\u043c\u043e\u0441\u0442\u043a\u043e\u043c \u0432 \u043c\u043c  \u0414\u0430\/\u041d\u0435\u0442","labourUnit":"\u043c2","labourPriceCell":"F12","labourQuantityCell":"E12","labourTotalCell":"G12","labourDecimalPlaces":2,"labourFormat":"0.00","labourAdditional":true,"labourAdditionalTitle":900},{"labourNumber":"2.","labourTitle":"\u0420\u0430\u0437\u0440\u0430\u0431\u043e\u0442\u043a\u0430 \u043a\u043e\u0442\u043b\u043e\u0432\u0430\u043d\u0430 \u0431\u0435\u0437 \u0432\u044b\u0432\u043e\u0437\u0430 \u0433\u0440\u0443\u043d\u0442\u0430 \u0441 \u043e\u0442\u043c\u043e\u0441\u0442\u043a\u043e\u043c \u0414\u0430\/\u041d\u0435\u0442","labourUnit":"\u043c3","labourPriceCell":"F13","labourQuantityCell":"E13","labourTotalCell":"G13","labourDecimalPlaces":3,"labourFormat":"0.000","labourAdditional":true,"labourAdditionalTitle":900},{"labourNumber":"3.","labourTitle":"\u0417\u0430\u0447\u0438\u0441\u0442\u043a\u0430 \u0434\u043d\u0430 \u043a\u043e\u0442\u043b\u043e\u0432\u0430\u043d\u0430 \u0432\u0440\u0443\u0447\u043d\u0443\u044e","labourUnit":"\u043c2","labourPriceCell":"F14","labourQuantityCell":"E14","labourTotalCell":"G14","labourDecimalPlaces":2,"labourFormat":"0.00","labourAdditional":false},{"labourNumber":"4.","labourTitle":"\u0420\u0430\u0437\u0440\u0430\u0431\u043e\u0442\u043a\u0430 \u0433\u0440\u0443\u043d\u0442\u0430 \u0425\u0412\u0421 \u0432 \u0440\u0443\u0447\u043d\u0443\u044e 1800\u0445400\u043c\u043c","labourUnit":"\u043c3","labourPriceCell":"F15","labourQuantityCell":"E15","labourTotalCell":"G15","labourDecimalPlaces":3,"labourFormat":"0.000","labourAdditional":false},{"labourNumber":"5.","labourTitle":"\u0423\u0441\u0442\u0440\u043e\u0439\u0441\u0442\u0432\u043e \u043e\u0441\u043d\u043e\u0432\u0430\u043d\u0438\u044f \u043f\u043e\u0434 \u0437\u0430\u043a\u043b\u0430\u0434\u043d\u0443\u044e \u0442\u0440\u0443\u0431\u0443, \"\u043f\u043e\u0441\u0442\u0435\u043b\u044c\u043a\u0430\" \u0441 \u043f\u043e\u0441\u043b\u0435\u0434\u0443\u044e\u0449\u0435\u0439 \u043e\u0431\u0432\u0430\u043b\u043e\u0432\u043a\u043e\u0439 \u043f\u0435\u0441\u043a\u043e\u043c \u0434\u043e 100 \u043c\u043c.","labourUnit":"\u043c3","labourPriceCell":"F16","labourQuantityCell":"E16","labourTotalCell":"G16","labourDecimalPlaces":3,"labourFormat":"0.000","labourAdditional":false},{"labourNumber":"6.","labourTitle":"\u0423\u043a\u043b\u0430\u0434\u043a\u0430 \u0442\u0440\u0443\u0431\u044b \u0432\u0432\u043e\u0434\u0430 \u0425\u0412\u0421 \u0441 \u0443\u0442\u0435\u043f\u043b\u0435\u043d\u0438\u0435\u043c \u0432 \u0432 \u0433\u0438\u043b\u044c\u0437\u0435 ","labourUnit":"\u043f.\u043c","labourPriceCell":"F17","labourQuantityCell":"E17","labourTotalCell":"G17","labourDecimalPlaces":1,"labourFormat":"0.0","labourAdditional":false},{"labourNumber":"7.","labourTitle":"\u041e\u0431\u0440\u0430\u0442\u043d\u0430\u044f \u0437\u0430\u0441\u044b\u043f\u043a\u0430 \u0442\u0440\u0430\u043d\u0448\u0435\u0438","labourUnit":"\u043c3","labourPriceCell":"F18","labourQuantityCell":"E18","labourTotalCell":"G18","labourDecimalPlaces":3,"labourFormat":"0.000","labourAdditional":false},{"labourNumber":null,"labourTitle":null,"labourUnit":null,"labourPriceCell":"F19","labourQuantityCell":"E19","labourTotalCell":"G19","labourDecimalPlaces":2,"labourFormat":"0.00","labourAdditional":false},{"labourNumber":null,"labourTitle":null,"labourUnit":null,"labourPriceCell":"F20","labourQuantityCell":"E20","labourTotalCell":"G20","labourDecimalPlaces":2,"labourFormat":"0.00","labourAdditional":false},{"labourNumber":null,"labourTitle":null,"labourUnit":null,"labourPriceCell":"F21","labourQuantityCell":"E21","labourTotalCell":"G21","labourDecimalPlaces":2,"labourFormat":"0.00","labourAdditional":false},{"labourNumber":null,"labourTitle":null,"labourUnit":null,"labourPriceCell":"F22","labourQuantityCell":"E22","labourTotalCell":"G22","labourDecimalPlaces":2,"labourFormat":"0.00","labourAdditional":false},{"labourNumber":"8.","labourTitle":"\u0420\u0430\u0437\u0440\u0430\u0431\u043e\u0442\u043a\u0430 \u0433\u0440\u0443\u043d\u0442\u0430 \u042d\u041e\u041c \u0432 \u0440\u0443\u0447\u043d\u0443\u044e 700\u0445400\u043c\u043c","labourUnit":"\u043c3","labourPriceCell":"F23","labourQuantityCell":"E23","labourTotalCell":"G23","labourDecimalPlaces":3,"labourFormat":"0.000","labourAdditional":false},{"labourNumber":"9.","labourTitle":"\u0423\u0441\u0442\u0440\u043e\u0439\u0441\u0442\u0432\u043e \u043e\u0441\u043d\u043e\u0432\u0430\u043d\u0438\u044f \u043f\u043e\u0434 \u0437\u0430\u043a\u043b\u0430\u0434\u043d\u0443\u044e \u0442\u0440\u0443\u0431\u0443, \"\u043f\u043e\u0441\u0442\u0435\u043b\u044c\u043a\u0430\", \u0441 \u043f\u043e\u0441\u043b\u0435\u0434\u0443\u044e\u0449\u0435\u0439 \u043e\u0431\u0432\u0430\u043b\u043e\u0432\u043a\u043e\u0439 \u043f\u0435\u0441\u043a\u043e\u043c \u0434\u043e 100 \u043c\u043c.","labourUnit":"\u043c3","labourPriceCell":"F24","labourQuantityCell":"E24","labourTotalCell":"G24","labourDecimalPlaces":3,"labourFormat":"0.000","labourAdditional":false},{"labourNumber":"10.","labourTitle":"\u0423\u043a\u043b\u0430\u0434\u043a\u0430 \u0442\u0440\u0443\u0431\u044b \u0432\u0432\u043e\u0434\u0430 \u042d\u041e\u041c","labourUnit":"\u043f.\u043c","labourPriceCell":"F25","labourQuantityCell":"E25","labourTotalCell":"G25","labourDecimalPlaces":1,"labourFormat":"0.0","labourAdditional":false},{"labourNumber":"11.","labourTitle":"\u041e\u0431\u0440\u0430\u0442\u043d\u0430\u044f \u0437\u0430\u0441\u044b\u043f\u043a\u0430 \u0442\u0440\u0430\u043d\u0448\u0435\u0438","labourUnit":"\u043c3","labourPriceCell":"F26","labourQuantityCell":"E26","labourTotalCell":"G26","labourDecimalPlaces":3,"labourFormat":"0.000","labourAdditional":false},{"labourNumber":"12.","labourTitle":"\u0420\u0430\u0437\u0440\u0430\u0431\u043e\u0442\u043a\u0430 \u0433\u0440\u0443\u043d\u0442\u0430 \u0421\u0421 \u0432 \u0440\u0443\u0447\u043d\u0443\u044e 700\u0445400\u043c\u043c","labourUnit":"\u043c3","labourPriceCell":"F27","labourQuantityCell":"E27","labourTotalCell":"G27","labourDecimalPlaces":3,"labourFormat":"0.000","labourAdditional":false},{"labourNumber":"13.","labourTitle":"\u0423\u0441\u0442\u0440\u043e\u0439\u0441\u0442\u0432\u043e \u043e\u0441\u043d\u043e\u0432\u0430\u043d\u0438\u044f \u043f\u043e\u0434 \u0437\u0430\u043a\u043b\u0430\u0434\u043d\u0443\u044e \u0442\u0440\u0443\u0431\u0443, \"\u043f\u043e\u0441\u0442\u0435\u043b\u044c\u043a\u0430\", \u0441 \u043f\u043e\u0441\u043b\u0435\u0434\u0443\u044e\u0449\u0435\u0439 \u043e\u0431\u0432\u0430\u043b\u043e\u0432\u043a\u043e\u0439 \u043f\u0435\u0441\u043a\u043e\u043c \u0434\u043e 100 \u043c\u043c.","labourUnit":"\u043c3","labourPriceCell":"F28","labourQuantityCell":"E28","labourTotalCell":"G28","labourDecimalPlaces":3,"labourFormat":"0.000","labourAdditional":false},{"labourNumber":"14.","labourTitle":"\u0423\u043a\u043b\u0430\u0434\u043a\u0430 \u0442\u0440\u0443\u0431\u044b \u0432\u0432\u043e\u0434\u0430 \u0421\u0421","labourUnit":"\u043f.\u043c","labourPriceCell":"F29","labourQuantityCell":"E29","labourTotalCell":"G29","labourDecimalPlaces":1,"labourFormat":"0.0","labourAdditional":false},{"labourNumber":"15.","labourTitle":"\u041e\u0431\u0440\u0430\u0442\u043d\u0430\u044f \u0437\u0430\u0441\u044b\u043f\u043a\u0430 \u0442\u0440\u0430\u043d\u0448\u0435\u0438","labourUnit":"\u043c3","labourPriceCell":"F30","labourQuantityCell":"E30","labourTotalCell":"G30","labourDecimalPlaces":3,"labourFormat":"0.000","labourAdditional":false},{"labourNumber":"16.","labourTitle":"\u0420\u0430\u0437\u0440\u0430\u0431\u043e\u0442\u043a\u0430 \u0433\u0440\u0443\u043d\u0442\u0430 \u043a\u0430\u043d\u0430\u043b\u0438\u0437\u0430\u0446\u0438\u044f \u0432 \u0440\u0443\u0447\u043d\u0443\u044e","labourUnit":"\u043c3","labourPriceCell":"F31","labourQuantityCell":"E31","labourTotalCell":"G31","labourDecimalPlaces":3,"labourFormat":"0.000","labourAdditional":false},{"labourNumber":"17.","labourTitle":"\u0423\u0441\u0442\u0440\u043e\u0439\u0441\u0442\u0432\u043e \u043e\u0441\u043d\u043e\u0432\u0430\u043d\u0438\u044f \u043f\u043e\u0434 \u0437\u0430\u043a\u043b\u0430\u0434\u043d\u0443\u044e \u0442\u0440\u0443\u0431\u0443, \"\u043f\u043e\u0441\u0442\u0435\u043b\u044c\u043a\u0430\", \u0441 \u043f\u043e\u0441\u043b\u0435\u0434\u0443\u044e\u0449\u0435\u0439 \u043e\u0431\u0432\u0430\u043b\u043e\u0432\u043a\u043e\u0439 \u043f\u0435\u0441\u043a\u043e\u043c \u0434\u043e 100 \u043c\u043c.","labourUnit":"\u043c3","labourPriceCell":"F32","labourQuantityCell":"E32","labourTotalCell":"G32","labourDecimalPlaces":3,"labourFormat":"0.000","labourAdditional":false},{"labourNumber":"18.","labourTitle":"\u0423\u043a\u043b\u0430\u0434\u043a\u0430 \u0442\u0440\u0443\u0431\u044b \u0432\u044b\u0432\u043e\u0434\u0430 \u043a\u0430\u043d\u0430\u043b\u0438\u0437\u0430\u0446\u0438\u0438","labourUnit":"\u043f.\u043c","labourPriceCell":"F33","labourQuantityCell":"E33","labourTotalCell":"G33","labourDecimalPlaces":1,"labourFormat":"0.0","labourAdditional":false},{"labourNumber":"19.","labourTitle":"\u041e\u0431\u0440\u0430\u0442\u043d\u0430\u044f \u0437\u0430\u0441\u044b\u043f\u043a\u0430 \u0442\u0440\u0430\u043d\u0448\u0435\u0438","labourUnit":"\u043c3","labourPriceCell":"F34","labourQuantityCell":"E34","labourTotalCell":"G34","labourDecimalPlaces":3,"labourFormat":"0.000","labourAdditional":false},{"labourNumber":null,"labourTitle":null,"labourUnit":null,"labourPriceCell":"F35","labourQuantityCell":"E35","labourTotalCell":"G35","labourDecimalPlaces":2,"labourFormat":"0.00","labourAdditional":false},{"labourNumber":"20.","labourTitle":"\u0412\u044b\u0440\u0430\u0432\u043d\u0438\u0432\u0430\u043d\u0438\u0435 \u0434\u043d\u0430 \u043a\u043e\u0442\u043b\u043e\u0432\u0430\u043d\u0430","labourUnit":"\u043c3","labourPriceCell":"F36","labourQuantityCell":"E36","labourTotalCell":"G36","labourDecimalPlaces":3,"labourFormat":"0.000","labourAdditional":false},{"labourNumber":"21.","labourTitle":"\u0423\u043a\u043b\u0430\u0434\u043a\u0430 \u0433\u0435\u043e\u0442\u0435\u043a\u0441\u0442\u0438\u043b\u044f \u043a\u043e\u0442\u043b\u043e\u0432\u0430\u043d","labourUnit":"\u043c2","labourPriceCell":"F37","labourQuantityCell":"E37","labourTotalCell":"G37","labourDecimalPlaces":2,"labourFormat":"0.00","labourAdditional":false},{"labourNumber":"22.","labourTitle":"\u0423\u0441\u0442\u0440\u043e\u0439\u0441\u0442\u0432\u043e \u043f\u0435\u0441\u0447\u0430\u043d\u043e\u0433\u043e \u043e\u0441\u043d\u043e\u0432\u0430\u043d\u0438\u044f \u0441 \u043f\u043e\u0441\u043b\u043e\u0439\u043d\u044b\u043c \u0442\u0440\u0430\u043c\u0431\u043e\u0432\u0430\u043d\u0438\u0435\u043c  \u0442\u043e\u043b\u0449\u0438\u043d\u043e\u0439 \u043c\u043c.","labourUnit":"\u043c3","labourPriceCell":"F38","labourQuantityCell":"E38","labourTotalCell":"G38","labourDecimalPlaces":3,"labourFormat":"0.000","labourAdditional":true,"labourAdditionalTitle":200},{"labourNumber":"23.","labourTitle":"\u0423\u0441\u0442\u0440\u043e\u0439\u0441\u0442\u0432\u043e \u0449\u0435\u0431\u0435\u043d\u043e\u0447\u043d\u043e\u0433\u043e \u043e\u0441\u043d\u043e\u0432\u0430\u043d\u0438\u044f \u0441 \u043f\u043e\u0441\u043b\u043e\u0439\u043d\u044b\u043c \u0442\u0440\u0430\u043c\u0431\u043e\u0432\u0430\u043d\u0438\u0435\u043c  \u0442\u043e\u043b\u0449\u0438\u043d\u043e\u0439 \u043c\u043c.","labourUnit":"\u043c3","labourPriceCell":"F39","labourQuantityCell":"E39","labourTotalCell":"G39","labourDecimalPlaces":3,"labourFormat":"0.000","labourAdditional":true,"labourAdditionalTitle":200},{"labourNumber":"24.","labourTitle":"\u0423\u0441\u0442\u0440\u043e\u0439\u0441\u0442\u0432\u043e \u0442\u0435\u043f\u043b\u043e\u0437\u0430\u0449\u0438\u0442\u043d\u043e\u0433\u043e \u0441\u043b\u043e\u044f \u0442\u043e\u043b\u0449\u0438\u043d\u043e\u0439 \u043c\u043c","labourUnit":"\u043c2","labourPriceCell":"F40","labourQuantityCell":"E40","labourTotalCell":"G40","labourDecimalPlaces":2,"labourFormat":"0.00","labourAdditional":true,"labourAdditionalTitle":50},{"labourNumber":"25.","labourTitle":"\u0423\u0441\u0442\u0440\u043e\u0439\u0441\u0442\u0432\u043e \u0431\u0435\u0442\u043e\u043d\u043d\u043e\u0433\u043e \u043e\u0441\u043d\u043e\u0432\u0430\u043d\u0438\u044f (\u043f\u043e\u0434\u0431\u0435\u0442\u043e\u043d\u043a\u0430)  \u0442\u043e\u043b\u0449\u0438\u043d\u043e\u0439 \u043c\u043c.","labourUnit":"\u043c3","labourPriceCell":"F41","labourQuantityCell":"E41","labourTotalCell":"G41","labourDecimalPlaces":3,"labourFormat":"0.000","labourAdditional":true,"labourAdditionalTitle":100},{"labourNumber":null,"labourTitle":null,"labourUnit":null,"labourPriceCell":"F42","labourQuantityCell":"E42","labourTotalCell":"G42","labourDecimalPlaces":2,"labourFormat":"0.00","labourAdditional":false}],"materialItems":[{"materialTitle":"\u0420\u0430\u0441\u0445\u043e\u0434\u043d\u044b\u0439 \u043c\u0430\u0442\u0435\u0440\u0438\u0430\u043b \u043d\u0430 \u0440\u0430\u0437\u0431\u0438\u0432\u043a\u0443 \u043f\u043b\u043e\u0449\u0430\u0434\u043a\u0438","materialUnit":"\u043a-\u043a\u0442","materialPriceCell":"L12","materialQuantityCell":"K12","materialTotalCell":"M12","materialDecimalPlaces":0,"materialFormat":"0","materialAdditional":false},{"materialTitle":null,"materialUnit":null,"materialPriceCell":"L13","materialQuantityCell":"K13","materialTotalCell":"M13","materialDecimalPlaces":2,"materialFormat":"0.00","materialAdditional":false},{"materialTitle":null,"materialUnit":null,"materialPriceCell":"L14","materialQuantityCell":"K14","materialTotalCell":"M14","materialDecimalPlaces":2,"materialFormat":"0.00","materialAdditional":false},{"materialTitle":null,"materialUnit":null,"materialPriceCell":"L15","materialQuantityCell":"K15","materialTotalCell":"M15","materialDecimalPlaces":2,"materialFormat":"0.00","materialAdditional":false},{"materialTitle":"\u041f\u0435\u0441\u043e\u043a","materialUnit":"\u043c3","materialPriceCell":"L16","materialQuantityCell":"K16","materialTotalCell":"M16","materialDecimalPlaces":3,"materialFormat":"0.000","materialAdditional":false},{"materialTitle":"\u0422\u0440\u0443\u0431\u0430 \u041f\u041d\u0414 32 \u0445 2.4 Pn12.5 SDR 13.","materialUnit":"\u043c.\u043f.","materialPriceCell":"L17","materialQuantityCell":"K17","materialTotalCell":"M17","materialDecimalPlaces":0,"materialFormat":"0","materialAdditional":false},{"materialTitle":"\u0423\u0442\u0435\u043f\u043b\u0438\u0442\u0435\u043b\u044c \u0442\u0440\u0443\u0431\u043d\u044b\u0439 \u041d\u041f\u042d 35*13\u043c\u043c\n(\u0434\u043b\u044f \u0442\u0440\u0443\u0431\u044b \u041f\u041d\u0414 \u041432) \u043e\u0442\u0440\u0435\u0437\u043e\u043a 2\u043c","materialUnit":"\u0448\u0442","materialPriceCell":"L18","materialQuantityCell":"K18","materialTotalCell":"M18","materialDecimalPlaces":0,"materialFormat":"0","materialAdditional":false},{"materialTitle":"\u0421\u043a\u043e\u0442\u0447 \u0441\u0430\u043d\u0442\u0435\u0445\u043d\u0438\u0447\u0435\u0441\u043a\u0438\u0439 \u0430\u0440\u043c\u0438\u0440\u043e\u0432\u0430\u043d\u043d\u044b\u0439 \u0441\u0435\u0440\u044b\u0439 UNIBOB 48\u043c\u043c \u0445 50\u043c","materialUnit":"\u0440\u043e\u043b","materialPriceCell":"L19","materialQuantityCell":"K19","materialTotalCell":"M19","materialDecimalPlaces":0,"materialFormat":"0","materialAdditional":false},{"materialTitle":"\u0422\u0440\u0443\u0431\u0430 \u0434\u043b\u044f \u043d\u0430\u0440\u0443\u0436\u043d\u043e\u0439 \u043a\u0430\u043d\u0430\u043b\u0438\u0437\u0430\u0446\u0438\u0438 \u041f\u0412\u0425 \u0433\u043b\u0430\u0434\u043a\u0430\u044f \u0440\u0430\u0441\u0442\u0440\u0443\u0431\u043d\u0430\u044f \u0440\u044b\u0436\u0430\u044f 110 \u0445 2,2 \u0445 1000 \u043c\u043c Sn4","materialUnit":"\u0448\u0442","materialPriceCell":"L20","materialQuantityCell":"K20","materialTotalCell":"M20","materialDecimalPlaces":0,"materialFormat":"0","materialAdditional":false},{"materialTitle":"\u0422\u0440\u0443\u0431\u0430 \u0434\u043b\u044f \u043d\u0430\u0440\u0443\u0436\u043d\u043e\u0439 \u043a\u0430\u043d\u0430\u043b\u0438\u0437\u0430\u0446\u0438\u0438 \u041f\u0412\u0425 \u0433\u043b\u0430\u0434\u043a\u0430\u044f \u0440\u0430\u0441\u0442\u0440\u0443\u0431\u043d\u0430\u044f \u0440\u044b\u0436\u0430\u044f 110 \u0445 2,2 \u0445 2000 \u043c\u043c Sn4","materialUnit":"\u0448\u0442","materialPriceCell":"L21","materialQuantityCell":"K21","materialTotalCell":"M21","materialDecimalPlaces":0,"materialFormat":"0","materialAdditional":false},{"materialTitle":"\u041e\u0442\u0432\u043e\u0434 110 \u043c\u043c x 30\u00b0 \u041f\u041f","materialUnit":"\u0448\u0442","materialPriceCell":"L22","materialQuantityCell":"K22","materialTotalCell":"M22","materialDecimalPlaces":0,"materialFormat":"0","materialAdditional":false},{"materialTitle":null,"materialUnit":null,"materialPriceCell":"L23","materialQuantityCell":"K23","materialTotalCell":"M23","materialDecimalPlaces":2,"materialFormat":"0.00","materialAdditional":false},{"materialTitle":"\u041f\u0435\u0441\u043e\u043a","materialUnit":"\u043c3","materialPriceCell":"L24","materialQuantityCell":"K24","materialTotalCell":"M24","materialDecimalPlaces":3,"materialFormat":"0.000","materialAdditional":false},{"materialTitle":"\u0422\u0440\u0443\u0431\u0430 \u041f\u041d\u0414 50 \u0445 3.0 Pn10 SDR 17 ","materialUnit":"\u043c.\u043f.","materialPriceCell":"L25","materialQuantityCell":"K25","materialTotalCell":"M25","materialDecimalPlaces":0,"materialFormat":"0","materialAdditional":false},{"materialTitle":null,"materialUnit":null,"materialPriceCell":"L26","materialQuantityCell":"K26","materialTotalCell":"M26","materialDecimalPlaces":2,"materialFormat":"0.00","materialAdditional":false},{"materialTitle":null,"materialUnit":null,"materialPriceCell":"L27","materialQuantityCell":"K27","materialTotalCell":"M27","materialDecimalPlaces":2,"materialFormat":"0.00","materialAdditional":false},{"materialTitle":"\u041f\u0435\u0441\u043e\u043a","materialUnit":"\u043c3","materialPriceCell":"L28","materialQuantityCell":"K28","materialTotalCell":"M28","materialDecimalPlaces":3,"materialFormat":"0.000","materialAdditional":false},{"materialTitle":"\u0422\u0440\u0443\u0431\u0430 \u041f\u041d\u0414 50 \u0445 3.0 Pn10 SDR 17 ","materialUnit":"\u043c.\u043f.","materialPriceCell":"L29","materialQuantityCell":"K29","materialTotalCell":"M29","materialDecimalPlaces":0,"materialFormat":"0","materialAdditional":false},{"materialTitle":null,"materialUnit":null,"materialPriceCell":"L30","materialQuantityCell":"K30","materialTotalCell":"M30","materialDecimalPlaces":2,"materialFormat":"0.00","materialAdditional":false},{"materialTitle":null,"materialUnit":null,"materialPriceCell":"L31","materialQuantityCell":"K31","materialTotalCell":"M31","materialDecimalPlaces":2,"materialFormat":"0.00","materialAdditional":false},{"materialTitle":"\u041f\u0435\u0441\u043e\u043a","materialUnit":"\u043c3","materialPriceCell":"L32","materialQuantityCell":"K32","materialTotalCell":"M32","materialDecimalPlaces":3,"materialFormat":"0.000","materialAdditional":false},{"materialTitle":"\u0422\u0440\u0443\u0431\u0430 \u0434\u043b\u044f \u043d\u0430\u0440\u0443\u0436\u043d\u043e\u0439 \u043a\u0430\u043d\u0430\u043b\u0438\u0437\u0430\u0446\u0438\u0438 \u041f\u0412\u0425 \u0433\u043b\u0430\u0434\u043a\u0430\u044f \u0440\u0430\u0441\u0442\u0440\u0443\u0431\u043d\u0430\u044f \u0440\u044b\u0436\u0430\u044f 110 \u0445 2,2 \u0445 2000 \u043c\u043c Sn4","materialUnit":"\u0448\u0442","materialPriceCell":"L33","materialQuantityCell":"K33","materialTotalCell":"M33","materialDecimalPlaces":0,"materialFormat":"0","materialAdditional":false},{"materialTitle":"\u0422\u0440\u0443\u0431\u0430 \u0434\u043b\u044f \u043d\u0430\u0440\u0443\u0436\u043d\u043e\u0439 \u043a\u0430\u043d\u0430\u043b\u0438\u0437\u0430\u0446\u0438\u0438 \u041f\u0412\u0425 \u0433\u043b\u0430\u0434\u043a\u0430\u044f \u0440\u0430\u0441\u0442\u0440\u0443\u0431\u043d\u0430\u044f \u0440\u044b\u0436\u0430\u044f 110 \u0445 2,2 \u0445 1000 \u043c\u043c Sn4","materialUnit":"\u0448\u0442","materialPriceCell":"L34","materialQuantityCell":"K34","materialTotalCell":"M34","materialDecimalPlaces":0,"materialFormat":"0","materialAdditional":false},{"materialTitle":"\u041e\u0442\u0432\u043e\u0434 110 \u043c\u043c x 90\u00b0 \u041f\u041f","materialUnit":"\u0448\u0442","materialPriceCell":"L35","materialQuantityCell":"K35","materialTotalCell":"M35","materialDecimalPlaces":0,"materialFormat":"0","materialAdditional":false},{"materialTitle":"\u041f\u0435\u0441\u043e\u043a","materialUnit":"\u043c3","materialPriceCell":"L36","materialQuantityCell":"K36","materialTotalCell":"M36","materialDecimalPlaces":3,"materialFormat":"0.000","materialAdditional":false},{"materialTitle":"\u0413\u0435\u043e\u0442\u0435\u043a\u0441\u0442\u0438\u043b\u044c 160 \u0433\u0440\/\u043c2","materialUnit":"\u043c2","materialPriceCell":"L37","materialQuantityCell":"K37","materialTotalCell":"M37","materialDecimalPlaces":2,"materialFormat":"0.00","materialAdditional":false},{"materialTitle":"\u041f\u0435\u0441\u043e\u043a","materialUnit":"\u043c3","materialPriceCell":"L38","materialQuantityCell":"K38","materialTotalCell":"M38","materialDecimalPlaces":3,"materialFormat":"0.000","materialAdditional":false},{"materialTitle":"\u0429\u0435\u0431\u0435\u043d\u044c \u0433\u0440\u0430\u0432\u0438\u0439\u043d\u044b\u0439 \u0444\u0440. 20-40","materialUnit":"\u043c3","materialPriceCell":"L39","materialQuantityCell":"K39","materialTotalCell":"M39","materialDecimalPlaces":3,"materialFormat":"0.000","materialAdditional":false},{"materialTitle":"\u042d\u041f\u041f\u0421  \u0442\u043e\u043b\u0449\u0438\u043d\u043e\u0439 \u043c\u043c.","materialUnit":"\u043f\u0430\u0447\u043a\u0430","materialPriceCell":"L40","materialQuantityCell":"K40","materialTotalCell":"M40","materialDecimalPlaces":0,"materialFormat":"0","materialAdditional":true,"materialAdditionalTitle":50},{"materialTitle":"\u0411\u0435\u0442\u043e\u043d \u041c100 \u0412 7,5","materialUnit":"\u043c3","materialPriceCell":"L41","materialQuantityCell":"K41","materialTotalCell":"M41","materialDecimalPlaces":3,"materialFormat":"0.000","materialAdditional":false},{"materialTitle":null,"materialUnit":null,"materialPriceCell":"L42","materialQuantityCell":"K42","materialTotalCell":"M42","materialDecimalPlaces":2,"materialFormat":"0.00","materialAdditional":false}],"sectionTotal":"G43","endRow":43},"2":{"value":"2. \u0423\u0441\u0442\u0440\u043e\u0439\u0441\u0442\u0432\u043e \u0444\u0443\u043d\u0434\u0430\u043c\u0435\u043d\u0442\u0430 ","colIndex":0,"rowIndex":43,"labourItems":[{"labourNumber":"1.","labourTitle":"\u0413\u0438\u0434\u0440\u043e\u0438\u0437\u043e\u043b\u044f\u0446\u0438\u044f \u0432 \u0434\u0432\u0430 \u0441\u043b\u043e\u044f (\u043f\u043e\u0434\u0431\u0435\u0442\u043e\u043d\u043a\u0430+\u0442\u043e\u0440\u0446\u044b \u043f\u043b\u0438\u0442\u044b)","labourUnit":"\u043c2","labourPriceCell":"F45","labourQuantityCell":"E45","labourTotalCell":"G45","labourDecimalPlaces":2,"labourFormat":"0.00","labourAdditional":false},{"labourNumber":null,"labourTitle":null,"labourUnit":null,"labourPriceCell":"F46","labourQuantityCell":"E46","labourTotalCell":"G46","labourDecimalPlaces":2,"labourFormat":"0.00","labourAdditional":false},{"labourNumber":null,"labourTitle":null,"labourUnit":null,"labourPriceCell":"F47","labourQuantityCell":"E47","labourTotalCell":"G47","labourDecimalPlaces":2,"labourFormat":"0.00","labourAdditional":false},{"labourNumber":"2.","labourTitle":"\u041c\u043e\u043d\u0442\u0430\u0436 \u043e\u043f\u0430\u043b\u0443\u0431\u043a\u0438","labourUnit":"\u043c2","labourPriceCell":"F48","labourQuantityCell":"E48","labourTotalCell":"G48","labourDecimalPlaces":2,"labourFormat":"0.00","labourAdditional":false},{"labourNumber":null,"labourTitle":null,"labourUnit":null,"labourPriceCell":"F49","labourQuantityCell":"E49","labourTotalCell":"G49","labourDecimalPlaces":2,"labourFormat":"0.00","labourAdditional":false},{"labourNumber":null,"labourTitle":null,"labourUnit":null,"labourPriceCell":"F50","labourQuantityCell":"E50","labourTotalCell":"G50","labourDecimalPlaces":2,"labourFormat":"0.00","labourAdditional":false},{"labourNumber":"3.","labourTitle":"\u0423\u0441\u0442\u0440\u043e\u0439\u0441\u0442\u0432\u043e \u043e\u0442\u0441\u0435\u0447\u043a\u0438 ","labourUnit":"\u043c2","labourPriceCell":"F51","labourQuantityCell":"E51","labourTotalCell":"G51","labourDecimalPlaces":2,"labourFormat":"0.00","labourAdditional":false},{"labourNumber":"4.","labourTitle":"\u0423\u0441\u0442\u0440\u043e\u0439\u0441\u0442\u0432\u043e \u0430\u0440\u043c\u043e\u043a\u0430\u0440\u043a\u0430\u0441\u0430 \u043c\u043e\u043d\u043e\u043b\u0438\u0442\u043d\u043e\u0439 \u043f\u043b\u0438\u0442\u044b","labourUnit":"\u0442\u043d","labourPriceCell":"F52","labourQuantityCell":"E52","labourTotalCell":"G52","labourDecimalPlaces":3,"labourFormat":"0.000","labourAdditional":false},{"labourNumber":null,"labourTitle":null,"labourUnit":null,"labourPriceCell":"F53","labourQuantityCell":"E53","labourTotalCell":"G53","labourDecimalPlaces":2,"labourFormat":"0.00","labourAdditional":false},{"labourNumber":null,"labourTitle":null,"labourUnit":null,"labourPriceCell":"F54","labourQuantityCell":"E54","labourTotalCell":"G54","labourDecimalPlaces":2,"labourFormat":"0.00","labourAdditional":false},{"labourNumber":"5.","labourTitle":"\u0418\u0437\u0433\u043e\u0442\u043e\u0432\u043b\u0435\u043d\u0438\u0435 \u0434\u0435\u0442\u0430\u043b\u0435\u0439 \"\u043b\u044f\u0433\u0443\u0448\u043a\u0430\"","labourUnit":"\u0448\u0442","labourPriceCell":"F55","labourQuantityCell":"E55","labourTotalCell":"G55","labourDecimalPlaces":0,"labourFormat":"0","labourAdditional":false},{"labourNumber":"6.","labourTitle":"\u0418\u0437\u0433\u043e\u0442\u043e\u0432\u043b\u0435\u043d\u0438\u0435 \u041f-\u043e\u0431\u0440\u0430\u0437\u043d\u044b\u0439 \u0445\u043e\u043c\u0443\u0442 \"\u0442\u043e\u0440\u0435\u0446\"","labourUnit":"\u0448\u0442","labourPriceCell":"F56","labourQuantityCell":"E56","labourTotalCell":"G56","labourDecimalPlaces":0,"labourFormat":"0","labourAdditional":false},{"labourNumber":null,"labourTitle":null,"labourUnit":null,"labourPriceCell":"F57","labourQuantityCell":"E57","labourTotalCell":"G57","labourDecimalPlaces":2,"labourFormat":"0.00","labourAdditional":false},{"labourNumber":"7.","labourTitle":"\u0423\u043a\u043b\u0430\u0434\u043a\u0430 \u0431\u0435\u0442\u043e\u043d\u043d\u043e\u0439 \u0441\u043c\u0435\u0441\u0438 \u043c\u043e\u043d\u043e\u043b\u0438\u0442\u043d\u043e\u0439 \u0444\u0443\u043d\u0434\u0430\u043c\u0435\u043d\u0442\u043d\u043e\u0439 \u043f\u043b\u0438\u0442\u044b","labourUnit":"\u043c3","labourPriceCell":"F58","labourQuantityCell":"E58","labourTotalCell":"G58","labourDecimalPlaces":3,"labourFormat":"0.000","labourAdditional":false},{"labourNumber":null,"labourTitle":null,"labourUnit":null,"labourPriceCell":"F59","labourQuantityCell":"E59","labourTotalCell":"G59","labourDecimalPlaces":2,"labourFormat":"0.00","labourAdditional":false},{"labourNumber":null,"labourTitle":null,"labourUnit":null,"labourPriceCell":"F60","labourQuantityCell":"E60","labourTotalCell":"G60","labourDecimalPlaces":2,"labourFormat":"0.00","labourAdditional":false},{"labourNumber":null,"labourTitle":null,"labourUnit":null,"labourPriceCell":"F61","labourQuantityCell":"E61","labourTotalCell":"G61","labourDecimalPlaces":2,"labourFormat":"0.00","labourAdditional":false},{"labourNumber":null,"labourTitle":null,"labourUnit":null,"labourPriceCell":"F62","labourQuantityCell":"E62","labourTotalCell":"G62","labourDecimalPlaces":2,"labourFormat":"0.00","labourAdditional":false},{"labourNumber":null,"labourTitle":null,"labourUnit":null,"labourPriceCell":"F63","labourQuantityCell":"E63","labourTotalCell":"G63","labourDecimalPlaces":2,"labourFormat":"0.00","labourAdditional":false},{"labourNumber":"8.","labourTitle":"\u0413\u0438\u0434\u0440\u043e\u0438\u0437\u043e\u043b\u044f\u0446\u0438\u044f \u043f\u043b\u0438\u0442\u044b \u0432 \u0434\u0432\u0430 \u0441\u043b\u043e\u044f (\u0432\u0435\u0440\u0445)","labourUnit":"\u043c2","labourPriceCell":"F64","labourQuantityCell":"E64","labourTotalCell":"G64","labourDecimalPlaces":2,"labourFormat":"0.00","labourAdditional":false},{"labourNumber":null,"labourTitle":null,"labourUnit":null,"labourPriceCell":"F65","labourQuantityCell":"E65","labourTotalCell":"G65","labourDecimalPlaces":2,"labourFormat":"0.00","labourAdditional":false},{"labourNumber":null,"labourTitle":null,"labourUnit":null,"labourPriceCell":"F66","labourQuantityCell":"E66","labourTotalCell":"G66","labourDecimalPlaces":2,"labourFormat":"0.00","labourAdditional":false},{"labourNumber":null,"labourTitle":null,"labourUnit":null,"labourPriceCell":"F67","labourQuantityCell":"E67","labourTotalCell":"G67","labourDecimalPlaces":2,"labourFormat":"0.00","labourAdditional":false},{"labourNumber":null,"labourTitle":null,"labourUnit":null,"labourPriceCell":"F68","labourQuantityCell":"E68","labourTotalCell":"G68","labourDecimalPlaces":2,"labourFormat":"0.00","labourAdditional":false}],"materialItems":[{"materialTitle":"\u0413\u0438\u0434\u0440\u043e\u0438\u0437\u043e\u043b","materialUnit":"\u0440\u0443\u043b","materialPriceCell":"L45","materialQuantityCell":"K45","materialTotalCell":"M45","materialDecimalPlaces":0,"materialFormat":"0","materialAdditional":false},{"materialTitle":"\u041c\u0430\u0441\u0442\u0438\u043a\u0430 \u0431\u0438\u0442\u0443\u043c\u043d\u0430\u044f \u211624 \u041c\u0413\u041d\u0422 (20 \u043a\u0433)","materialUnit":"\u0432\u0435\u0434\u0440\u043e","materialPriceCell":"L46","materialQuantityCell":"K46","materialTotalCell":"M46","materialDecimalPlaces":0,"materialFormat":"0","materialAdditional":false},{"materialTitle":"\u0413\u0430\u0437 \u0431\u0430\u043b\u043b\u043e\u043d\u043d\u044b\u0439 50 \u043b","materialUnit":"\u0448\u0442","materialPriceCell":"L47","materialQuantityCell":"K47","materialTotalCell":"M47","materialDecimalPlaces":0,"materialFormat":"0","materialAdditional":false},{"materialTitle":"\u0414\u043e\u0441\u043a\u0430 50\u0445100 \u043e\u0431\u0440","materialUnit":"\u043c3","materialPriceCell":"L48","materialQuantityCell":"K48","materialTotalCell":"M48","materialDecimalPlaces":3,"materialFormat":"0.000","materialAdditional":false},{"materialTitle":"\u0413\u0432\u043e\u0437\u0434\u044c \u0441\u0442\u0440\u043e\u0438\u0442\u0435\u043b\u044c\u043d\u044b\u0439  100 \u043c\u043c","materialUnit":"\u043a\u0433","materialPriceCell":"L49","materialQuantityCell":"K49","materialTotalCell":"M49","materialDecimalPlaces":3,"materialFormat":"0.000","materialAdditional":false},{"materialTitle":"\u0421\u0430\u043c\u043e\u0440\u0435\u0437 \u0447\u0435\u0440\u043d\u044b\u0439 \u043f\u043e \u0434\u0435\u0440\u0435\u0432\u0443 \u0443\u0441\u0438\u043b\u0435\u043d\u043d\u044b\u0439 96 \u043c\u043c","materialUnit":"\u043a\u0433","materialPriceCell":"L50","materialQuantityCell":"K50","materialTotalCell":"M50","materialDecimalPlaces":3,"materialFormat":"0.000","materialAdditional":false},{"materialTitle":"\u041f\u043b\u0435\u043d\u043a\u0430 \u043f\/\u044d 200 \u043c\u043a\u0440","materialUnit":"\u043c2","materialPriceCell":"L51","materialQuantityCell":"K51","materialTotalCell":"M51","materialDecimalPlaces":2,"materialFormat":"0.00","materialAdditional":false},{"materialTitle":null,"materialUnit":null,"materialPriceCell":"L52","materialQuantityCell":"K52","materialTotalCell":"M52","materialDecimalPlaces":2,"materialFormat":"0.00","materialAdditional":false},{"materialTitle":"\u0410\u0440\u043c\u0430\u0442\u0443\u0440\u0430 \u0410500\u0421 (\u0432\u0435\u0440\u0445\u043d\u0435\u0435 \u0430\u0440\u043c\u0438\u0440\u043e\u0432.) \u0434\u0438\u0430\u043c\u0435\u0442\u0440 \u043c\u043c.","materialUnit":"\u0442\u043d","materialPriceCell":"L53","materialQuantityCell":"K53","materialTotalCell":"M53","materialDecimalPlaces":3,"materialFormat":"0.000","materialAdditional":true,"materialAdditionalTitle":12},{"materialTitle":"\u0410\u0440\u043c\u0430\u0442\u0443\u0440\u0430 \u0410500\u0421 (\u043d\u0438\u0436\u043d\u0435\u0435 \u0430\u0440\u043c\u0438\u0440\u043e\u0432.) \u0434\u0438\u0430\u043c\u0435\u0442\u0440 \u043c\u043c.","materialUnit":"\u0442\u043d","materialPriceCell":"L54","materialQuantityCell":"K54","materialTotalCell":"M54","materialDecimalPlaces":3,"materialFormat":"0.000","materialAdditional":true,"materialAdditionalTitle":12},{"materialTitle":"\u0410\u0440\u043c\u0430\u0442\u0443\u0440\u0430 \u0434.8 \u043c\u043c  \u0410240","materialUnit":"\u0442\u043d","materialPriceCell":"L55","materialQuantityCell":"K55","materialTotalCell":"M55","materialDecimalPlaces":3,"materialFormat":"0.000","materialAdditional":false},{"materialTitle":"\u0410\u0440\u043c\u0430\u0442\u0443\u0440\u0430 \u0410500\u0421 \u0434.10 \u043c\u043c  ","materialUnit":"\u0442\u043d","materialPriceCell":"L56","materialQuantityCell":"K56","materialTotalCell":"M56","materialDecimalPlaces":3,"materialFormat":"0.000","materialAdditional":false},{"materialTitle":"\u041f\u0440\u043e\u0432\u043e\u043b\u043e\u043a\u0430 \u0432\u044f\u0437\u0430\u043b\u044c\u043d\u0430\u044f ","materialUnit":"\u0442\u043d","materialPriceCell":"L57","materialQuantityCell":"K57","materialTotalCell":"M57","materialDecimalPlaces":3,"materialFormat":"0.000","materialAdditional":false},{"materialTitle":"\u0411\u0435\u0442\u043e\u043d \u0412 25","materialUnit":"\u043c3","materialPriceCell":"L58","materialQuantityCell":"K58","materialTotalCell":"M58","materialDecimalPlaces":3,"materialFormat":"0.000","materialAdditional":false},{"materialTitle":"\u041e\u043f\u043e\u0440\u043d\u0430\u044f \u043f\u043b\u043e\u0449\u0430\u0434\u043a\u0430 \"\u0421\u0442\u0443\u043b\u044c\u0447\u0438\u043a\"","materialUnit":"\u0448\u0442","materialPriceCell":"L59","materialQuantityCell":"K59","materialTotalCell":"M59","materialDecimalPlaces":0,"materialFormat":"0","materialAdditional":false},{"materialTitle":"\u0420\u0430\u0441\u0445\u043e\u0434\u043d\u044b\u0435 \u043c\u0430\u0442\u0435\u0440\u0438\u0430\u043b\u044b","materialUnit":null,"materialPriceCell":"L60","materialQuantityCell":"K60","materialTotalCell":"M60","materialDecimalPlaces":2,"materialFormat":"0.00","materialAdditional":false},{"materialTitle":"\u0434\u0438\u0441\u043a \u043e\u0442\u0440\u0435\u0437\u043d\u043e\u0439 \u0434 125 \u043c\u043c","materialUnit":"\u0448\u0442","materialPriceCell":"L61","materialQuantityCell":"K61","materialTotalCell":"M61","materialDecimalPlaces":0,"materialFormat":"0","materialAdditional":false},{"materialTitle":"\u0441\u043e\u0431\u043a\u0430 \u0434\u043b\u044f \u0441\u0442\u0435\u043f\u043b\u0435\u0440\u0430 1000 \u0448\u0442","materialUnit":"\u043f\u0430\u0447.","materialPriceCell":"L62","materialQuantityCell":"K62","materialTotalCell":"M62","materialDecimalPlaces":0,"materialFormat":"0","materialAdditional":false},{"materialTitle":"\u043d\u0438\u0442\u043a\u0430 \u0440\u0430\u0437\u043c\u0435\u0442\u043e\u0447\u043d\u0430\u044f 150 \u043c","materialUnit":"\u0431\u0443\u0445","materialPriceCell":"L63","materialQuantityCell":"K63","materialTotalCell":"M63","materialDecimalPlaces":0,"materialFormat":"0","materialAdditional":false},{"materialTitle":"\u0413\u0438\u0434\u0440\u043e\u0438\u0437\u043e\u043b","materialUnit":"\u0440\u0443\u043b","materialPriceCell":"L64","materialQuantityCell":"K64","materialTotalCell":"M64","materialDecimalPlaces":0,"materialFormat":"0","materialAdditional":false},{"materialTitle":"\u041c\u0430\u0441\u0442\u0438\u043a\u0430 \u0431\u0438\u0442\u0443\u043c\u043d\u0430\u044f \u211624 \u041c\u0413\u041d\u0422 (20 \u043a\u0433)","materialUnit":"\u0432\u0435\u0434\u0440\u043e","materialPriceCell":"L65","materialQuantityCell":"K65","materialTotalCell":"M65","materialDecimalPlaces":0,"materialFormat":"0","materialAdditional":false},{"materialTitle":"\u0413\u0430\u0437 \u0431\u0430\u043b\u043b\u043e\u043d\u043d\u044b\u0439 50 \u043b","materialUnit":"\u0448\u0442","materialPriceCell":"L66","materialQuantityCell":"K66","materialTotalCell":"M66","materialDecimalPlaces":0,"materialFormat":"0","materialAdditional":false},{"materialTitle":null,"materialUnit":null,"materialPriceCell":"L67","materialQuantityCell":"K67","materialTotalCell":"M67","materialDecimalPlaces":2,"materialFormat":"0.00","materialAdditional":false},{"materialTitle":null,"materialUnit":null,"materialPriceCell":"L68","materialQuantityCell":"K68","materialTotalCell":"M68","materialDecimalPlaces":2,"materialFormat":"0.00","materialAdditional":false}],"sectionTotal":"G69","endRow":69},"3":{"value":"3. \u041e\u0442\u043c\u043e\u0441\u0442\u043e\u043a","colIndex":0,"rowIndex":69,"labourItems":[{"labourNumber":1,"labourTitle":"\u0413\u0438\u0434\u0440\u043e\u0438\u0437\u043e\u043b\u044f\u0446\u0438\u044f \u0432 \u0434\u0432\u0430 \u0441\u043b\u043e\u044f","labourUnit":"\u043c2","labourPriceCell":"F71","labourQuantityCell":"E71","labourTotalCell":"G71","labourDecimalPlaces":2,"labourFormat":"0.00","labourAdditional":false},{"labourNumber":null,"labourTitle":null,"labourUnit":null,"labourPriceCell":"F72","labourQuantityCell":"E72","labourTotalCell":"G72","labourDecimalPlaces":2,"labourFormat":"0.00","labourAdditional":false},{"labourNumber":null,"labourTitle":null,"labourUnit":null,"labourPriceCell":"F73","labourQuantityCell":"E73","labourTotalCell":"G73","labourDecimalPlaces":2,"labourFormat":"0.00","labourAdditional":false},{"labourNumber":2,"labourTitle":"\u041c\u043e\u043d\u0442\u0430\u0436 \u043e\u043f\u0430\u043b\u0443\u0431\u043a\u0438","labourUnit":"\u043c2","labourPriceCell":"F74","labourQuantityCell":"E74","labourTotalCell":"G74","labourDecimalPlaces":2,"labourFormat":"0.00","labourAdditional":false},{"labourNumber":null,"labourTitle":null,"labourUnit":null,"labourPriceCell":"F75","labourQuantityCell":"E75","labourTotalCell":"G75","labourDecimalPlaces":2,"labourFormat":"0.00","labourAdditional":false},{"labourNumber":3,"labourTitle":"\u0423\u0441\u0442\u0440\u043e\u0439\u0441\u0442\u0432\u043e \u043e\u0442\u043c\u043e\u0441\u0442\u043a\u0430 \u0442\u043e\u043b\u0449 120-150 \u043c\u043c","labourUnit":"\u043c2","labourPriceCell":"F76","labourQuantityCell":"E76","labourTotalCell":"G76","labourDecimalPlaces":2,"labourFormat":"0.00","labourAdditional":false},{"labourNumber":null,"labourTitle":null,"labourUnit":null,"labourPriceCell":"F77","labourQuantityCell":"E77","labourTotalCell":"G77","labourDecimalPlaces":2,"labourFormat":"0.00","labourAdditional":false},{"labourNumber":null,"labourTitle":null,"labourUnit":null,"labourPriceCell":"F78","labourQuantityCell":"E78","labourTotalCell":"G78","labourDecimalPlaces":2,"labourFormat":"0.00","labourAdditional":false}],"materialItems":[{"materialTitle":"\u0413\u0438\u0434\u0440\u043e\u0438\u0437\u043e\u043b","materialUnit":"\u0440\u0443\u043b","materialPriceCell":"L71","materialQuantityCell":"K71","materialTotalCell":"M71","materialDecimalPlaces":0,"materialFormat":"0","materialAdditional":false},{"materialTitle":"\u041c\u0430\u0441\u0442\u0438\u043a\u0430 \u0431\u0438\u0442\u0443\u043c\u043d\u0430\u044f \u211624 \u041c\u0413\u041d\u0422 (20 \u043a\u0433)","materialUnit":"\u0448\u0442","materialPriceCell":"L72","materialQuantityCell":"K72","materialTotalCell":"M72","materialDecimalPlaces":0,"materialFormat":"0","materialAdditional":false},{"materialTitle":"\u0413\u0430\u0437 \u0431\u0430\u043b\u043b\u043e\u043d\u043d\u044b\u0439 50 \u043b","materialUnit":"\u0448\u0442","materialPriceCell":"L73","materialQuantityCell":"K73","materialTotalCell":"M73","materialDecimalPlaces":0,"materialFormat":"0","materialAdditional":false},{"materialTitle":"\u0414\u043e\u0441\u043a\u0430 50\u0445150 \u043e\u0431\u0440","materialUnit":"\u043c3","materialPriceCell":"L74","materialQuantityCell":"K74","materialTotalCell":"M74","materialDecimalPlaces":3,"materialFormat":"0.000","materialAdditional":false},{"materialTitle":"\u0413\u0432\u043e\u0437\u0434\u044c \u0441\u0442\u0440\u043e\u0438\u0442\u0435\u043b\u044c\u043d\u044b\u0439  100 \u043c\u043c","materialUnit":"\u043a\u0433","materialPriceCell":"L75","materialQuantityCell":"K75","materialTotalCell":"M75","materialDecimalPlaces":3,"materialFormat":"0.000","materialAdditional":false},{"materialTitle":"\u0410\u0440\u043c\u0430\u0442\u0443\u0440\u0430 \u0434.12 \u0410500\u0421","materialUnit":"\u0442\u043d","materialPriceCell":"L76","materialQuantityCell":"K76","materialTotalCell":"M76","materialDecimalPlaces":3,"materialFormat":"0.000","materialAdditional":false},{"materialTitle":"\u041f\u0440\u043e\u0432\u043e\u043b\u043e\u043a\u0430 \u0432\u044f\u0437\u0430\u043b\u044c\u043d\u0430\u044f ","materialUnit":"\u0442\u043d","materialPriceCell":"L77","materialQuantityCell":"K77","materialTotalCell":"M77","materialDecimalPlaces":3,"materialFormat":"0.000","materialAdditional":false},{"materialTitle":"\u0411\u0435\u0442\u043e\u043d \u0412 25","materialUnit":"\u043c3","materialPriceCell":"L78","materialQuantityCell":"K78","materialTotalCell":"M78","materialDecimalPlaces":3,"materialFormat":"0.000","materialAdditional":false}],"sectionTotal":"G79","endRow":79},"4":{"value":"4. \u0422\u0440\u0430\u043d\u0441\u043f\u043e\u0440\u0442\u043d\u044b\u0435 \u0440\u0430\u0441\u0445\u043e\u0434\u044b \u0438 \u0430\u0440\u0435\u043d\u0434\u0430 \u043c\u0435\u0445\u0430\u043d\u0438\u0437\u043c\u043e\u0432","colIndex":0,"rowIndex":79,"labourItems":[{"labourNumber":"1.","labourTitle":"\u041f\u0440\u0438\u0435\u043c \u043c\u0430\u0442\u0435\u0440\u0430\u043b\u043e\u0432 \u043d\u0430 \u0444\u0443\u043d\u0434\u0430\u043c\u0435\u043d\u0442","labourUnit":"\u0442\u043d","labourPriceCell":"F81","labourQuantityCell":"E81","labourTotalCell":"G81","labourDecimalPlaces":3,"labourFormat":"0.000","labourAdditional":false},{"labourNumber":null,"labourTitle":null,"labourUnit":null,"labourPriceCell":"F82","labourQuantityCell":"E82","labourTotalCell":"G82","labourDecimalPlaces":2,"labourFormat":"0.00","labourAdditional":false},{"labourNumber":null,"labourTitle":null,"labourUnit":null,"labourPriceCell":"F83","labourQuantityCell":"E83","labourTotalCell":"G83","labourDecimalPlaces":2,"labourFormat":"0.00","labourAdditional":false},{"labourNumber":null,"labourTitle":null,"labourUnit":null,"labourPriceCell":"F84","labourQuantityCell":"E84","labourTotalCell":"G84","labourDecimalPlaces":2,"labourFormat":"0.00","labourAdditional":false},{"labourNumber":null,"labourTitle":null,"labourUnit":null,"labourPriceCell":"F85","labourQuantityCell":"E85","labourTotalCell":"G85","labourDecimalPlaces":2,"labourFormat":"0.00","labourAdditional":false}],"materialItems":[{"materialTitle":"\u0410\u0440\u0435\u043d\u0434\u0430 \u0430\/\u043c \u0434\u043e 1,5 \u0442\u043d","materialUnit":"\u043c\/\u0441\u043c","materialPriceCell":"L81","materialQuantityCell":"K81","materialTotalCell":"M81","materialDecimalPlaces":2,"materialFormat":"0.00","materialAdditional":false},{"materialTitle":"\u0410\u0440\u0435\u043d\u0434\u0430 \u0430\/\u043c \u0434\u043e 3,5 \u0442\u043d","materialUnit":"\u043c\/\u0441\u043c","materialPriceCell":"L82","materialQuantityCell":"K82","materialTotalCell":"M82","materialDecimalPlaces":2,"materialFormat":"0.00","materialAdditional":false},{"materialTitle":"\u0410\u0440\u0435\u043d\u0434\u0430 \u0430\/\u043c \u0434\u043e 8 \u0442\u043d","materialUnit":"\u043c\/\u0441\u043c","materialPriceCell":"L83","materialQuantityCell":"K83","materialTotalCell":"M83","materialDecimalPlaces":2,"materialFormat":"0.00","materialAdditional":false},{"materialTitle":"\u0410\u0440\u0435\u043d\u0434\u0430 JSB 42\u043c3\/\u0441\u043c","materialUnit":"\u043c\/\u0441\u043c","materialPriceCell":"L84","materialQuantityCell":"K84","materialTotalCell":"M84","materialDecimalPlaces":2,"materialFormat":"0.00","materialAdditional":false},{"materialTitle":"\u0410\u0440\u0435\u043d\u0434\u0430 \u0431\u0435\u0442\u043e\u043d\u043e\u043d\u0430\u0441\u043e\u0441\u0430","materialUnit":"\u043c\/\u0441\u043c","materialPriceCell":"L85","materialQuantityCell":"K85","materialTotalCell":"M85","materialDecimalPlaces":2,"materialFormat":"0.00","materialAdditional":false}],"sectionTotal":"G86","endRow":86}},"endOfLabour":{"col":"G","colIndex":6},"lastLetter":{"col":"M","colIndex":12},"otherCols":{"labourNumber":0,"labourTitle":1,"labourUnit":3,"labourQuantity":4,"labourPrice":5,"labourTotal":6,"materialTitle":7,"materialUnit":9,"materialQuantity":10,"materialPrice":11,"materialTotal":12},"boxStart":{"rowIndex":89,"col":"H","firstCell":"H89"}}}